pxshot/__init__.py
pxshot/async_client.py
pxshot/client.py
pxshot/exceptions.py
pxshot/models.py
pxshot/py.typed
pxshot-1.0.0.dist-info/METADATA
pxshot-1.0.0.dist-info/WHEEL
pxshot-1.0.0.dist-info/licenses/LICENSE
pxshot-1.0.0.dist-info/RECORD
